oineus-0.9.19.dist-info/RECORD
oineus-0.9.19.dist-info/WHEEL
oineus-0.9.19.dist-info/METADATA
oineus/__init__.py
oineus/_oineus.cpython-312-darwin.so
oineus/diff/__init__.py
